{"annotations":{"list":[{"builtIn":1,"datasource":{"type":"grafana","uid":"-- Grafana --"},"enable":true,"hide":true,"iconColor":"rgba(0, 211, 255, 1)","name":"Annotations & Alerts","target":{"limit":100,"matchAny":false,"tags":[],"type":"dashboard"},"type":"dashboard"}]},"editable":true,"fiscalYearStartMonth":0,"graphTooltip":0,"id":1,"links":[],"liveNow":false,"panels":[{"gridPos":{"h":8,"w":12,"x":0,"y":0},"id":2,"options":{"reduceOptions":{"calcs":["lastNotNull"],"fields":"","values":false},"showThresholdLabels":false,"showThresholdMarkers":true,"text":{}},"pluginVersion":"9.5.1","targets":[{"datasource":{"type":"prometheus","uid":"P1A1B885E0C0E482C"},"expr":"sum(api_requests_total)","instant":true,"legendFormat":"Total Requests","range":true}],"title":"Total API Requests","type":"stat"},{"gridPos":{"h":8,"w":12,"x":12,"y":0},"id":4,"options":{"reduceOptions":{"calcs":["lastNotNull"],"fields":"","values":false},"showThresholdLabels":false,"showThresholdMarkers":true,"text":{}},"pluginVersion":"9.5.1","targets":[{"datasource":{"type":"prometheus","uid":"P1A1B885E0C0E482C"},"expr":"sum(predictions_total)","instant":true,"legendFormat":"Total Predictions","range":true}],"title":"Total Predictions Made","type":"stat"},{"gridPos":{"h":8,"w":12,"x":0,"y":8},"id":6,"options":{"legend":{"displayMode":"list","placement":"bottom","showLegend":true},"pieType":"pie","tooltip":{"mode":"single","sort":"none"}},"pluginVersion":"9.5.1","targets":[{"datasource":{"type":"prometheus","uid":"P1A1B885E0C0E482C"},"expr":"sum(predictions_total) by (predicted_class)","legendFormat":"{{predicted_class}}","range":true}],"title":"Prediction Distribution","type":"piechart"},{"gridPos":{"h":8,"w":12,"x":12,"y":8},"id":8,"options":{"colorMode":"palette-classic","graphMode":"area","justifyMode":"auto","orientation":"auto","reduceOptions":{"calcs":["lastNotNull"],"fields":"","values":false},"showPercent":false,"textMode":"auto","wide":false},"pluginVersion":"9.5.1","targets":[{"datasource":{"type":"prometheus","uid":"P1A1B885E0C0E482C"},"expr":"sum(api_requests_total) by (endpoint)","legendFormat":"{{endpoint}}","range":true}],"title":"Requests by Endpoint","type":"barchart"},{"gridPos":{"h":8,"w":12,"x":0,"y":16},"id":10,"options":{"axisCenteredZero":false,"axisColorMode":"text","axisLabel":"","axisPlacement":"auto","barAlignment":0,"drawStyle":"line","fillOpacity":25,"gradientMode":"opacity","hideFrom":{"legend":false,"tooltip":false,"viz":false},"lineInterpolation":"smooth","lineWidth":1,"pointSize":5,"scaleDistribution":{"type":"linear"},"showPoints":"auto","spanNulls":false,"stacking":{"group":"A","mode":"none"},"tooltip":{"mode":"multi","sort":"none"}},"pluginVersion":"9.5.1","targets":[{"datasource":{"type":"prometheus","uid":"P1A1B885E0C0E482C"},"expr":"rate(api_request_duration_seconds_sum[5m]) / rate(api_request_duration_seconds_count[5m])","legendFormat":"Average Latency","range":true}],"title":"Average API Latency","type":"timeseries"},{"gridPos":{"h":8,"w":12,"x":12,"y":16},"id":12,"options":{"heatmap":{},"hideFrom":{"legend":false,"tooltip":false,"viz":false},"tooltip":{"mode":"single","sort":"none"}},"pluginVersion":"9.5.1","targets":[{"datasource":{"type":"prometheus","uid":"P1A1B885E0C0E482C"},"expr":"sum(rate(api_request_duration_seconds_bucket[5m])) by (le)","format":"heatmap","legendFormat":"{{le}}","range":true}],"title":"Request Latency Heatmap","type":"heatmap"}],"refresh":"","schemaVersion":38,"style":"dark","tags":[],"templating":{"list":[]},"time":{"from":"now-1h","to":"now"},"timepicker":{},"timezone":"","title":"MLOps API Monitoring","uid":"a4b3f2e0-f2b7-4a1e-8e5c-1d3c0a5b7d9c","version":1,"weekStart":""}